orderly_evm_connector/__init__.py
orderly_evm_connector/__version__.py
orderly_evm_connector/api.py
orderly_evm_connector/async_api.py
orderly_evm_connector/error.py
orderly_evm_connector/lib/__init__.py
orderly_evm_connector/lib/constants.py
orderly_evm_connector/lib/enums.py
orderly_evm_connector/lib/utils.py
orderly_evm_connector/rest/__init__.py
orderly_evm_connector/rest/_account.py
orderly_evm_connector/rest/_broker.py
orderly_evm_connector/rest/_campaign.py
orderly_evm_connector/rest/_delegate_signer.py
orderly_evm_connector/rest/_general.py
orderly_evm_connector/rest/_liquidation.py
orderly_evm_connector/rest/_market.py
orderly_evm_connector/rest/_notifications.py
orderly_evm_connector/rest/_referral.py
orderly_evm_connector/rest/_rewards.py
orderly_evm_connector/rest/_settlement.py
orderly_evm_connector/rest/_strategy_vault.py
orderly_evm_connector/rest/_system.py
orderly_evm_connector/rest/_trade.py
orderly_evm_connector/rest/_wallet.py
orderly_evm_connector/websocket/async_websocket_manager.py
orderly_evm_connector/websocket/orderly_socket_manager.py
orderly_evm_connector/websocket/websocket_api/__init__.py
orderly_evm_connector/websocket/websocket_api/_private_stream.py
orderly_evm_connector/websocket/websocket_api/_stream.py
orderly_evm_connector/websocket/websocket_client.py
orderly_evm_connector-0.2.6.dist-info/METADATA
orderly_evm_connector-0.2.6.dist-info/WHEEL
orderly_evm_connector-0.2.6.dist-info/licenses/LICENSE.md
orderly_evm_connector-0.2.6.dist-info/RECORD
