Metadata-Version: 2.4
Name: orderly-evm-connector
Version: 0.2.6
Summary: This is a lightweight library that works as a connector to Orderly API and Websocket.
License: MIT
License-File: LICENSE.md
Author: Orderly Tech
Requires-Python: >=3.10,<4
Classifier: License :: OSI Approved :: MIT License
Classifier: Programming Language :: Python :: 3
Classifier: Programming Language :: Python :: 3.10
Classifier: Programming Language :: Python :: 3.11
Classifier: Programming Language :: Python :: 3.12
Classifier: Programming Language :: Python :: 3.13
Classifier: Programming Language :: Python :: 3.14
Requires-Dist: aiohttp (>=3.9.5,<4.0.0)
Requires-Dist: asgiref (>=3.8.1,<4.0.0)
Requires-Dist: base58 (>=2.1.1,<3.0.0)
Requires-Dist: cryptography (>=42.0.8,<43.0.0)
Requires-Dist: eth-account (>=0.10.0,<0.11.0)
Requires-Dist: requests (>=2.31.0,<3.0.0)
Requires-Dist: sync-to-async (>=0.1.1,<0.2.0)
Requires-Dist: web3 (>=6.13.0,<7.0.0)
Requires-Dist: websocket-client (>=1.7.0,<2.0.0)
